api_lib/__init__.py
api_lib/api_lib.py
api_lib/method.py
api_lib/headers/__init__.py
api_lib/headers/accept.py
api_lib/headers/authorization.py
api_lib/headers/header.py
api_lib/objects/__init__.py
api_lib/objects/request.py
api_lib/objects/response.py
api_lib-0.0.4.dist-info/METADATA
api_lib-0.0.4.dist-info/WHEEL
api_lib-0.0.4.dist-info/licenses/LICENSE
api_lib-0.0.4.dist-info/RECORD
