Metadata-Version: 2.4
Name: api-lib
Version: 0.0.4
Project-URL: Homepage, https://github.com/jeandemeusy/api-lib
Project-URL: Issues, https://github.com/jeandemeusy/api-lib/issues
Author-email: Jean Demeusy <jean.demeusy@hoprnet.org>
Maintainer-email: Jean Demeusy <jean.demeusy@hoprnet.org>
License-Expression: MIT
License-File: LICENSE
Classifier: Programming Language :: Python :: 3.13
Requires-Python: ==3.13.*
Requires-Dist: aiohttp>=3.12.13
